{"cameraMode":{"drawMode":0,"name":"Shaded","section":"Shading Mode"},"sceneLighting":false,"audioPlay":false,"sceneViewState":{"m_AlwaysRefresh":false,"showFog":true,"showSkybox":false,"showFlares":true,"showImageEffects":true,"showParticleSystems":true,"showVisualEffectGraphs":true,"m_FxEnabled":true},"in2DMode":false,"pivot":{"x":24.195919036865236,"y":15.81144905090332,"z":36.386863708496097},"rotation":{"x":0.19188085198402406,"y":-0.35057616233825686,"z":0.07217491418123245,"w":0.9141407012939453},"size":4.29319953918457,"orthographic":false}